{
  "requirements": [
    {
      "bonus": false,
      "description": "1 - Vamos consultar uma API que fornece os valores de crypto moedas",
      "enabled": true,
      "identifier": null,
      "order": 1,
      "skill_ids": []
    },
    {
      "bonus": false,
      "description": "2 - Agora vamos fazer com que as moedas apareçam na tela",
      "enabled": true,
      "identifier": null,
      "order": 2,
      "skill_ids": []
    },
    {
      "bonus": false,
      "description": "3 - Mostrar somente as 10 primeiras moedas da requisição",
      "enabled": true,
      "identifier": null,
      "order": 3,
      "skill_ids": []
    }
  ]
}